{
  "event_id": "C2025R3",
  "fit_date": "2026-05-07",
  "H": 9.1115,
  "n": 6.2671,
  "rmse": 0.7983,
  "n_points": 89,
  "ephemeris": [
    {
      "date": "2026-05-07",
      "r": 0.643384595581,
      "delta": 0.69931933931273,
      "t_mag": 9.164,
      "predicted_mag": 5.33,
      "s_o_t": 39.2358,
      "s_o_t_flag": "/T",
      "t_o_m": 137.0,
      "mn_illu": 76.6506
    },
    {
      "date": "2026-05-08",
      "r": 0.657961281749,
      "delta": 0.73140743062287,
      "t_mag": 9.366,
      "predicted_mag": 5.58,
      "s_o_t": 40.6263,
      "s_o_t_flag": "/T",
      "t_o_m": 130.5,
      "mn_illu": 68.1462
    },
    {
      "date": "2026-05-09",
      "r": 0.672890691502,
      "delta": 0.76423393041728,
      "t_mag": 9.567,
      "predicted_mag": 5.83,
      "s_o_t": 41.8016,
      "s_o_t_flag": "/T",
      "t_o_m": 123.1,
      "mn_illu": 58.8255
    },
    {
      "date": "2026-05-10",
      "r": 0.688135384101,
      "delta": 0.79761332654364,
      "t_mag": 9.764,
      "predicted_mag": 6.08,
      "s_o_t": 42.7876,
      "s_o_t_flag": "/T",
      "t_o_m": 115.1,
      "mn_illu": 48.9479
    },
    {
      "date": "2026-05-11",
      "r": 0.703661038705,
      "delta": 0.83139136377552,
      "t_mag": 9.958,
      "predicted_mag": 6.32,
      "s_o_t": 43.6076,
      "s_o_t_flag": "/T",
      "t_o_m": 106.5,
      "mn_illu": 38.8275
    },
    {
      "date": "2026-05-12",
      "r": 0.71943629208,
      "delta": 0.86544001756845,
      "t_mag": 10.149,
      "predicted_mag": 6.56,
      "s_o_t": 44.2825,
      "s_o_t_flag": "/T",
      "t_o_m": 97.3,
      "mn_illu": 28.8554
    },
    {
      "date": "2026-05-13",
      "r": 0.735432557255,
      "delta": 0.89965311064021,
      "t_mag": 10.336,
      "predicted_mag": 6.79,
      "s_o_t": 44.8304,
      "s_o_t_flag": "/T",
      "t_o_m": 87.6,
      "mn_illu": 19.5166
    },
    {
      "date": "2026-05-14",
      "r": 0.751623832667,
      "delta": 0.93394258218708,
      "t_mag": 10.519,
      "predicted_mag": 7.02,
      "s_o_t": 45.2673,
      "s_o_t_flag": "/T",
      "t_o_m": 77.5,
      "mn_illu": 11.3863
    },
    {
      "date": "2026-05-15",
      "r": 0.767986508975,
      "delta": 0.96823536418426,
      "t_mag": 10.697,
      "predicted_mag": 7.25,
      "s_o_t": 45.6071,
      "s_o_t_flag": "/T",
      "t_o_m": 67.3,
      "mn_illu": 5.0913
    },
    {
      "date": "2026-05-16",
      "r": 0.784499178785,
      "delta": 1.00247079558792,
      "t_mag": 10.872,
      "predicted_mag": 7.47,
      "s_o_t": 45.8617,
      "s_o_t_flag": "/T",
      "t_o_m": 57.4,
      "mn_illu": 1.2257
    },
    {
      "date": "2026-05-17",
      "r": 0.801142452952,
      "delta": 1.03659849776671,
      "t_mag": 11.043,
      "predicted_mag": 7.68,
      "s_o_t": 46.0417,
      "s_o_t_flag": "/T",
      "t_o_m": 48.4,
      "mn_illu": 0.2319
    },
    {
      "date": "2026-05-18",
      "r": 0.817898785889,
      "delta": 1.07057663440183,
      "t_mag": 11.21,
      "predicted_mag": 7.89,
      "s_o_t": 46.1563,
      "s_o_t_flag": "/T",
      "t_o_m": 41.4,
      "mn_illu": 2.2865
    },
    {
      "date": "2026-05-19",
      "r": 0.834752311383,
      "delta": 1.10437048332625,
      "t_mag": 11.372,
      "predicted_mag": 8.1,
      "s_o_t": 46.2133,
      "s_o_t_flag": "/T",
      "t_o_m": 37.6,
      "mn_illu": 7.2421
    },
    {
      "date": "2026-05-20",
      "r": 0.851688689684,
      "delta": 1.13795125646502,
      "t_mag": 11.531,
      "predicted_mag": 8.3,
      "s_o_t": 46.2198,
      "s_o_t_flag": "/T",
      "t_o_m": 38.2,
      "mn_illu": 14.6568
    },
    {
      "date": "2026-05-21",
      "r": 0.868694966138,
      "delta": 1.17129511685592,
      "t_mag": 11.686,
      "predicted_mag": 8.5,
      "s_o_t": 46.1819,
      "s_o_t_flag": "/T",
      "t_o_m": 42.7,
      "mn_illu": 23.8963
    },
    {
      "date": "2026-05-22",
      "r": 0.885759441225,
      "delta": 1.20438235566409,
      "t_mag": 11.837,
      "predicted_mag": 8.69,
      "s_o_t": 46.1048,
      "s_o_t_flag": "/T",
      "t_o_m": 49.8,
      "mn_illu": 34.2609
    },
    {
      "date": "2026-05-23",
      "r": 0.902871551661,
      "delta": 1.23719670315619,
      "t_mag": 11.985,
      "predicted_mag": 8.88,
      "s_o_t": 45.9932,
      "s_o_t_flag": "/T",
      "t_o_m": 58.3,
      "mn_illu": 45.0874
    },
    {
      "date": "2026-05-24",
      "r": 0.920021761997,
      "delta": 1.26972475396752,
      "t_mag": 12.129,
      "predicted_mag": 9.06,
      "s_o_t": 45.8514,
      "s_o_t_flag": "/T",
      "t_o_m": 67.5,
      "mn_illu": 55.8066
    },
    {
      "date": "2026-05-25",
      "r": 0.937201466097,
      "delta": 1.30195548978206,
      "t_mag": 12.27,
      "predicted_mag": 9.24,
      "s_o_t": 45.6829,
      "s_o_t_flag": "/T",
      "t_o_m": 76.9,
      "mn_illu": 65.9584
    },
    {
      "date": "2026-05-26",
      "r": 0.95440289779,
      "delta": 1.33387988391327,
      "t_mag": 12.408,
      "predicted_mag": 9.42,
      "s_o_t": 45.4911,
      "s_o_t_flag": "/T",
      "t_o_m": 86.4,
      "mn_illu": 75.1827
    },
    {
      "date": "2026-05-27",
      "r": 0.971619049997,
      "delta": 1.36549057366196,
      "t_mag": 12.542,
      "predicted_mag": 9.59,
      "s_o_t": 45.2787,
      "s_o_t_flag": "/T",
      "t_o_m": 95.7,
      "mn_illu": 83.2009
    },
    {
      "date": "2026-05-28",
      "r": 0.988843601636,
      "delta": 1.39678158813294,
      "t_mag": 12.673,
      "predicted_mag": 9.76,
      "s_o_t": 45.0485,
      "s_o_t_flag": "/T",
      "t_o_m": 104.8,
      "mn_illu": 89.7987
    },
    {
      "date": "2026-05-29",
      "r": 1.006070851607,
      "delta": 1.42774812122866,
      "t_mag": 12.802,
      "predicted_mag": 9.93,
      "s_o_t": 44.8028,
      "s_o_t_flag": "/T",
      "t_o_m": 113.6,
      "mn_illu": 94.8148
    },
    {
      "date": "2026-05-30",
      "r": 1.023295659247,
      "delta": 1.45838634152788,
      "t_mag": 12.927,
      "predicted_mag": 10.09,
      "s_o_t": 44.5436,
      "s_o_t_flag": "/T",
      "t_o_m": 121.9,
      "mn_illu": 98.1352
    },
    {
      "date": "2026-05-31",
      "r": 1.040513390617,
      "delta": 1.48869323249622,
      "t_mag": 13.049,
      "predicted_mag": 10.25,
      "s_o_t": 44.2728,
      "s_o_t_flag": "/T",
      "t_o_m": 129.3,
      "mn_illu": 99.6912
    },
    {
      "date": "2026-06-01",
      "r": 1.057719870091,
      "delta": 1.51866645788904,
      "t_mag": 13.169,
      "predicted_mag": 10.4,
      "s_o_t": 43.9922,
      "s_o_t_flag": "/T",
      "t_o_m": 135.7,
      "mn_illu": 99.4595
    },
    {
      "date": "2026-06-02",
      "r": 1.074911336716,
      "delta": 1.54830424826605,
      "t_mag": 13.287,
      "predicted_mag": 10.55,
      "s_o_t": 43.7033,
      "s_o_t_flag": "/T",
      "t_o_m": 140.2,
      "mn_illu": 97.4611
    },
    {
      "date": "2026-06-03",
      "r": 1.092084404873,
      "delta": 1.57760530528623,
      "t_mag": 13.401,
      "predicted_mag": 10.7,
      "s_o_t": 43.4076,
      "s_o_t_flag": "/T",
      "t_o_m": 142.4,
      "mn_illu": 93.7588
    },
    {
      "date": "2026-06-04",
      "r": 1.10923602882,
      "delta": 1.60656872094825,
      "t_mag": 13.514,
      "predicted_mag": 10.85,
      "s_o_t": 43.1063,
      "s_o_t_flag": "/T",
      "t_o_m": 141.6,
      "mn_illu": 88.4533
    },
    {
      "date": "2026-06-05",
      "r": 1.126363470711,
      "delta": 1.63519390928472,
      "t_mag": 13.623,
      "predicted_mag": 10.99,
      "s_o_t": 42.8008,
      "s_o_t_flag": "/T",
      "t_o_m": 138.1,
      "mn_illu": 81.6803
    },
    {
      "date": "2026-06-06",
      "r": 1.143464271762,
      "delta": 1.66348054830405,
      "t_mag": 13.731,
      "predicted_mag": 11.13,
      "s_o_t": 42.492,
      "s_o_t_flag": "/T",
      "t_o_m": 132.3,
      "mn_illu": 73.6095
    }
  ]
}